README.md
kp_boot_32u4_cli.py
setup.py
kp_boot_32u4/__init__.py
kp_boot_32u4/constants.py
kp_boot_32u4/protocol.py
kp_boot_32u4/version.py
kp_boot_32u4.egg-info/PKG-INFO
kp_boot_32u4.egg-info/SOURCES.txt
kp_boot_32u4.egg-info/dependency_links.txt
kp_boot_32u4.egg-info/not-zip-safe
kp_boot_32u4.egg-info/requires.txt
kp_boot_32u4.egg-info/top_level.txt