Metadata-Version: 1.0
Name: kp-boot-32u4
Version: 0.0.2
Summary: Python library for kp_boot_32u4 AVR USB bootloader
Home-page: http://github.com/ahtn/kp_boot_32u4
Author: jem
Author-email: jem@seethis.link
License: MIT
Keywords: usb,hid,avr,atmega32u4,bootloader
Platform: UNKNOWN
